datasouls_antispoof/__init__.py
datasouls_antispoof/class_mapping.py
datasouls_antispoof/dataloaders.py
datasouls_antispoof/inference.py
datasouls_antispoof/pre_trained_models.py
datasouls_antispoof/train.py
datasouls_antispoof-0.0.4.dist-info/LICENSE
datasouls_antispoof-0.0.4.dist-info/METADATA
datasouls_antispoof-0.0.4.dist-info/WHEEL
datasouls_antispoof-0.0.4.dist-info/top_level.txt
datasouls_antispoof-0.0.4.dist-info/RECORD
