Metadata-Version: 2.1
Name: datasouls-antispoof
Version: 0.0.4
Summary: Detect spoofing attack
Home-page: https://github.com/ternaus/datasouls_antispoof
Author: Vladimir Iglovikov
License: MIT
Platform: UNKNOWN
Classifier: License :: OSI Approved :: MIT License
Classifier: Intended Audience :: Developers
Classifier: Intended Audience :: Science/Research
Classifier: Operating System :: OS Independent
Classifier: Programming Language :: Python
Classifier: Programming Language :: Python :: 3
Classifier: Topic :: Software Development :: Libraries
Classifier: Topic :: Software Development :: Libraries :: Python Modules
Requires-Dist: timm
Requires-Dist: torch
Requires-Dist: torchvision
Provides-Extra: test
Requires-Dist: pytest ; extra == 'test'
